getmyip/__init__.py
getmyip/myip.py
myIPstats-1.4.dist-info/LICENSE
myIPstats-1.4.dist-info/METADATA
myIPstats-1.4.dist-info/WHEEL
myIPstats-1.4.dist-info/top_level.txt
myIPstats-1.4.dist-info/RECORD
