Metadata-Version: 2.1
Name: myIPstats
Version: 1.4
Summary: A module to fetch your IP address information.
Home-page: https://github.com/ericdennis7/myIPstats
Author: Eric Dennis
Author-email: ericdennis11@gmail.com
License: MIT
Platform: UNKNOWN
Classifier: Programming Language :: Python :: 3
Classifier: Operating System :: OS Independent
Classifier: License :: OSI Approved :: MIT License
License-File: LICENSE
